LICENSE.txt
README.md
setup.cfg
setup.py
src/WireMockLibrary/__init__.py
src/WireMockLibrary/library.py
src/WireMockLibrary/version.py
src/robotframework_wiremock.egg-info/PKG-INFO
src/robotframework_wiremock.egg-info/SOURCES.txt
src/robotframework_wiremock.egg-info/dependency_links.txt
src/robotframework_wiremock.egg-info/requires.txt
src/robotframework_wiremock.egg-info/top_level.txt